saspt/__init__.py
saspt/constants.py
saspt/dataset.py
saspt/defoc.py
saspt/io.py
saspt/lik.py
saspt/parameters.py
saspt/plot.py
saspt/sa.py
saspt/trajectory_group.py
saspt/utils.py
saspt/samples/sample_tracks.csv
saspt/splines/fbm_defoc_splines_dz-0.1.csv
saspt/splines/fbm_defoc_splines_dz-0.2.csv
saspt/splines/fbm_defoc_splines_dz-0.3.csv
saspt/splines/fbm_defoc_splines_dz-0.4.csv
saspt/splines/fbm_defoc_splines_dz-0.5.csv
saspt/splines/fbm_defoc_splines_dz-0.6.csv
saspt/splines/fbm_defoc_splines_dz-0.7.csv
saspt/splines/fbm_defoc_splines_dz-0.8.csv
saspt/splines/fbm_defoc_splines_dz-0.9.csv
saspt/splines/fbm_defoc_splines_dz-1.0.csv
saspt/splines/fbm_defoc_splines_dz-1.1.csv
saspt/splines/fbm_defoc_splines_dz-1.2.csv
saspt/splines/fbm_defoc_splines_dz-1.3.csv
saspt/splines/fbm_defoc_splines_dz-1.4.csv
saspt/splines/fbm_defoc_splines_dz-1.5.csv
saspt/splines/fbm_defoc_splines_dz-1.6.csv
saspt-0.4.0.dist-info/LICENSE
saspt-0.4.0.dist-info/METADATA
saspt-0.4.0.dist-info/WHEEL
saspt-0.4.0.dist-info/top_level.txt
saspt-0.4.0.dist-info/RECORD
