Metadata-Version: 2.1
Name: saspt
Version: 0.4.0
Summary: State arrays for single particle tracking
Home-page: https://github.com/alecheckert/saspt
Author: Alec Heckert
Author-email: alecheckert@gmail.com
Classifier: Programming Language :: Python :: 3
Classifier: License :: OSI Approved :: MIT License
Classifier: Operating System :: OS Independent
Requires-Python: >=3.6
License-File: LICENSE
Requires-Dist: numpy
Requires-Dist: scipy
Requires-Dist: pandas
Requires-Dist: matplotlib
Requires-Dist: seaborn
Requires-Dist: tqdm
Requires-Dist: dask
